pyasl/__init__.py
pyasl/asl_mricloud.py
pyasl/asltbx.py
pyasl/data_import.py
pyasl/dlasl.py
pyasl/oxford_asl.py
pyasl/preclinical_MTI_PASL.py
pyasl/preclinical_pCASL.py
pyasl/models/model_068.hdf5
pyasl/models/model_099.hdf5
pyasl/tpm/TPM.nii
pyasl/utils/__init__.py
pyasl/utils/models.py
pyasl/utils/utils.py
pyasltst-0.1.2.dist-info/LICENSE
pyasltst-0.1.2.dist-info/METADATA
pyasltst-0.1.2.dist-info/WHEEL
pyasltst-0.1.2.dist-info/top_level.txt
pyasltst-0.1.2.dist-info/RECORD
