Metadata-Version: 2.1
Name: pyasltst
Version: 0.1.2
Summary: A standardized, open-source Python library for processing human and preclinical ASL MRI data.
Home-page: https://github.com/Trico01/PyASL
Author: Trico
Author-email: trico010725@gmail.com
License: MIT License
Classifier: Programming Language :: Python :: 3
Classifier: License :: OSI Approved :: MIT License
Classifier: Operating System :: OS Independent
Requires-Python: >=3.6
License-File: LICENSE
Requires-Dist: numpy >=1.20
Requires-Dist: nibabel >=3.2.0
Requires-Dist: nipype >=1.5.1
Requires-Dist: scipy >=1.7.0
Requires-Dist: scikit-image >=0.19.0
Requires-Dist: pandas >=1.5.0
Requires-Dist: tensorflow >=2.10
Requires-Dist: matplotlib >=3.5
Requires-Dist: pyyaml >=6.0
Requires-Dist: fsspec >=2022.5.0
Requires-Dist: jinja2 >=3.0
Requires-Dist: typing-extensions >=4.8.0
